docs/__init__.py
docs/gensite.py
omnic/__init__.py
omnic/builtin/__init__.py
omnic/builtin/converters/__init__.py
omnic/builtin/converters/audio.py
omnic/builtin/converters/chemical.py
omnic/builtin/converters/document.py
omnic/builtin/converters/git.py
omnic/builtin/converters/manifest.py
omnic/builtin/converters/mesh.py
omnic/builtin/converters/nodejs.py
omnic/builtin/converters/thumb.py
omnic/builtin/converters/vector.py
omnic/builtin/converters/video.py
omnic/builtin/converters/templates/git-tree.html
omnic/builtin/converters/templates/inline-js-variable.js
omnic/builtin/responses/__init__.py
omnic/builtin/responses/placeholders.py
omnic/builtin/services/__init__.py
omnic/builtin/services/media.py
omnic/builtin/services/test.py
omnic/builtin/services/admin/__init__.py
omnic/builtin/services/admin/urls.py
omnic/builtin/services/admin/views.py
omnic/builtin/services/admin/templates/.index.html.swp
omnic/builtin/services/admin/templates/base.html
omnic/builtin/services/admin/templates/graph.html
omnic/builtin/services/admin/templates/index.html
omnic/builtin/services/admin/templates/workers.html
omnic/builtin/services/admin/templates/zoo.html
omnic/builtin/services/viewer/__init__.py
omnic/builtin/services/viewer/converters.py
omnic/builtin/services/viewer/urls.py
omnic/builtin/services/viewer/views.py
omnic/builtin/services/viewer/static/spinner.gif
omnic/builtin/services/viewer/templates/base.html
omnic/builtin/services/viewer/templates/iffy.js
omnic/builtin/services/viewer/templates/index.html
omnic/builtin/services/viewer/templates/master-viewer-index.js
omnic/builtin/services/viewer/templates/playbutton.svg
omnic/builtin/services/viewer/templates/reload-thumb.js
omnic/builtin/services/viewer/templates/reload-viewers.js
omnic/builtin/services/viewer/templates/template_top.html
omnic/builtin/types/__init__.py
omnic/builtin/types/core.py
omnic/builtin/types/git.py
omnic/builtin/types/nodejs.py
omnic-0.1.16.dist-info/DESCRIPTION.rst
omnic-0.1.16.dist-info/METADATA
omnic-0.1.16.dist-info/RECORD
omnic-0.1.16.dist-info/WHEEL
omnic-0.1.16.dist-info/metadata.json
omnic-0.1.16.dist-info/top_level.txt
