Metadata-Version: 2.0
Name: omnic
Version: 0.1.16
Summary: Mostly stateless microservice framework for generating on-the-fly thumbs and previews of a wide variety of file types.
Home-page: https://github.com/michaelpb/omnic
Author: michaelb
Author-email: michaelpb@gmail.com
License: GPL3
Keywords: omnic
Platform: UNKNOWN
Classifier: Development Status :: 3 - Alpha
Classifier: Intended Audience :: Developers
Classifier: Natural Language :: English
Classifier: Framework :: AsyncIO
Classifier: Topic :: Multimedia :: Graphics :: Graphics Conversion
Classifier: Programming Language :: Python :: 3 :: Only
Classifier: Programming Language :: Python :: 3.5
Classifier: Programming Language :: Python :: 3.6
Classifier: License :: OSI Approved :: GNU General Public License v3 or later (GPLv3+)
Requires-Dist: aiohttp
Requires-Dist: async-timeout
Requires-Dist: python-magic
